NR_GUI/__init__.py
calculator_ONLY_FOR_TESTING-0.1.dist-info/LICENCE.txt
calculator_ONLY_FOR_TESTING-0.1.dist-info/METADATA
calculator_ONLY_FOR_TESTING-0.1.dist-info/WHEEL
calculator_ONLY_FOR_TESTING-0.1.dist-info/top_level.txt
calculator_ONLY_FOR_TESTING-0.1.dist-info/RECORD
